[
  {
    "id": "wzdvalvevertical_v01",
    "name": "wzdValveVertical_v01",
    "description": "A wzdValveVertical_v01.",
    "fileType": "vizw",
    "previewImageUrl": "",
    "downloadUrl": "",
    "tags": [
      "Valve",
      "Flow Control",
      "Actuator",
      "Water"
    ]
  },
  {
    "id": "wzdvalvehorizontal_v01",
    "name": "wzdValveHorizontal_v01",
    "description": "A wzdValveHorizontal_v01.",
    "fileType": "vizw",
    "previewImageUrl": "",
    "downloadUrl": "",
    "tags": [
      "Valve",
      "Flow Control",
      "Actuator",
      "Water"
    ]
  }
]