[
  {
    "id": "water reservoir tank 1",
    "name": "Water Reservoir Tank 1",
    "description": "A Water Reservoir Tank 1.",
    "fileType": "viz",
    "previewImageUrl": "",
    "downloadUrl": "",
    "tags": [
      "Tank",
      "Storage",
      "Containment",
      "Process"
    ]
  },
  {
    "id": "water tower tank 2",
    "name": "Water Tower Tank 2",
    "description": "A Water Tower Tank 2.",
    "fileType": "viz",
    "previewImageUrl": "",
    "downloadUrl": "",
    "tags": [
      "Tank",
      "Storage",
      "Containment",
      "Process"
    ]
  },
  {
    "id": "water tower tank 3",
    "name": "Water Tower Tank 3",
    "description": "A Water Tower Tank 3.",
    "fileType": "viz",
    "previewImageUrl": "",
    "downloadUrl": "",
    "tags": [
      "Tank",
      "Storage",
      "Containment",
      "Process"
    ]
  },
  {
    "id": "reservoir dam wall",
    "name": "Reservoir Dam Wall",
    "description": "A Reservoir Dam Wall.",
    "fileType": "viz",
    "previewImageUrl": "",
    "downloadUrl": "",
    "tags": []
  },
  {
    "id": "water tower tank 4",
    "name": "Water Tower Tank 4",
    "description": "A Water Tower Tank 4.",
    "fileType": "viz",
    "previewImageUrl": "",
    "downloadUrl": "",
    "tags": [
      "Tank",
      "Storage",
      "Containment",
      "Process"
    ]
  },
  {
    "id": "reservoir round dam",
    "name": "Reservoir Round Dam",
    "description": "A Reservoir Round Dam.",
    "fileType": "viz",
    "previewImageUrl": "",
    "downloadUrl": "",
    "tags": []
  },
  {
    "id": "reservoir dam",
    "name": "Reservoir Dam",
    "description": "A Reservoir Dam.",
    "fileType": "viz",
    "previewImageUrl": "",
    "downloadUrl": "",
    "tags": []
  },
  {
    "id": "water reservoir tank 2",
    "name": "Water Reservoir Tank 2",
    "description": "A Water Reservoir Tank 2.",
    "fileType": "viz",
    "previewImageUrl": "",
    "downloadUrl": "",
    "tags": [
      "Tank",
      "Storage",
      "Containment",
      "Process"
    ]
  },
  {
    "id": "water tower tank 1",
    "name": "Water Tower Tank 1",
    "description": "A Water Tower Tank 1.",
    "fileType": "viz",
    "previewImageUrl": "",
    "downloadUrl": "",
    "tags": [
      "Tank",
      "Storage",
      "Containment",
      "Process"
    ]
  }
]