[
  {
    "id": "analog quarter dial 1",
    "name": "Analog Quarter Dial 1",
    "description": "A Analog Quarter Dial 1.",
    "previewImageUrl": "Analog Quarter Dial 1.png",
    "downloadUrl": "Analog Quarter Dial 1.png",
    "tags": [
      "Analog",
      "Quarter",
      "Dial"
    ]
  },
  {
    "id": "analog quarter dial 2",
    "name": "Analog Quarter Dial 2",
    "description": "A Analog Quarter Dial 2.",
    "previewImageUrl": "Analog Quarter Dial 2.png",
    "downloadUrl": "Analog Quarter Dial 2.png",
    "tags": [
      "Analog",
      "Quarter",
      "Dial"
    ]
  },
  {
    "id": "analog quarter dial 3",
    "name": "Analog Quarter Dial 3",
    "description": "A Analog Quarter Dial 3.",
    "previewImageUrl": "Analog Quarter Dial 3.png",
    "downloadUrl": "Analog Quarter Dial 3.png",
    "tags": [
      "Analog",
      "Quarter",
      "Dial"
    ]
  }
]